{"skeleton":{"hash":"fkwJMkDbmUg","spine":"4.1.23","x":-239.86,"y":0.04,"width":1919.52,"height":991.75,"images":"./images/","audio":"/Users/proberts/Creative Cloud Files/Power Words/Sparky"},"bones":[{"name":"root","x":1075.69,"y":571.83},{"name":"body-main","parent":"root","length":126.99,"rotation":-88.24,"x":107.48,"y":-198.86,"scaleX":0.6545,"scaleY":0.6545},{"name":"body jet","parent":"body-main","length":40.23,"rotation":0.63,"x":351.53,"y":-1.27},{"name":"body jet small","parent":"body jet","length":17.26,"rotation":-0.79,"x":43.75,"y":0.07},{"name":"tail-top","parent":"body-main","length":60.14,"rotation":85.82,"x":314.75,"y":151.37},{"name":"arm-right-top","parent":"body-main","length":124.36,"rotation":47.06,"x":56.62,"y":157.5},{"name":"arm-left-top","parent":"body-main","length":119.3,"rotation":-46.38,"x":41.18,"y":-170.3},{"name":"neck-jet","parent":"body-main","x":12.41,"y":2.79},{"name":"head","parent":"body-main","length":276.13,"rotation":178.62,"x":-32.4,"y":4.16},{"name":"head-ear-right-top","parent":"head","length":100,"rotation":-169.21,"x":314.29,"y":-197.48},{"name":"head-ear-left","parent":"head","length":275.22,"rotation":148.22,"x":388.04,"y":114.03},{"name":"head-eyes","parent":"head","x":276.63,"y":77.1},{"name":"mouth","parent":"head","x":99.61,"y":153.55},{"name":"ring-1","parent":"body-main","length":82.48,"rotation":-1.76,"x":435.64,"y":-1.22},{"name":"ring-2","parent":"body-main","length":82.48,"rotation":-1.76,"x":435.64,"y":-1.22},{"name":"ring-3","parent":"body-main","length":82.48,"rotation":-1.76,"x":435.64,"y":-1.22},{"name":"head-ear-right-mid","parent":"head-ear-right-top","length":118.45,"rotation":-1.53,"x":100.81,"y":-0.53},{"name":"head-ear-right-end","parent":"head-ear-right-mid","length":114.65,"rotation":-1.06,"x":119.12,"y":-0.11},{"name":"snout-base","parent":"head","length":132.65,"rotation":72.72,"x":16.68,"y":-106.66},{"name":"snout-mid","parent":"snout-base","length":129.75,"rotation":-17.6,"x":139.75,"y":-1.66},{"name":"snout-end","parent":"snout-mid","length":115.07,"rotation":-29.67,"x":137.78,"y":0.11},{"name":"snout-nose","parent":"snout-end","x":118.34,"y":-7.15},{"name":"head-goggles","parent":"head","x":301.91,"y":65.81},{"name":"arm-right-mid","parent":"arm-right-top","length":82.91,"x":124.36},{"name":"arm-right-end","parent":"arm-right-mid","length":41.45,"x":82.91},{"name":"arm-left-mid","parent":"arm-left-top","length":79.53,"x":119.3},{"name":"arm-left-end","parent":"arm-left-mid","length":39.77,"x":79.53},{"name":"tail-mid","parent":"tail-top","length":67.55,"rotation":18.13,"x":59.95,"y":1.29},{"name":"tail-end","parent":"tail-mid","length":57.51,"rotation":16.3,"x":67.55},{"name":"body-top","parent":"body-main","x":42.56,"y":-3.66},{"name":"arm-right-target","parent":"body-main","rotation":88.24,"x":200.35,"y":309.08,"color":"ff3f00ff"},{"name":"arm-left-target","parent":"body-main","rotation":88.24,"x":183.32,"y":-318.86,"color":"ff3f00ff"},{"name":"body-mid","parent":"body-main","length":125.77,"rotation":0.31,"x":129.73,"y":-1.32},{"name":"body-end","parent":"body-mid","length":86.09,"rotation":-0.56,"x":127.99,"y":-1.21},{"name":"body-charger","parent":"body-main","x":208.58,"y":-16.2,"shearY":-4.48},{"name":"layout-size","parent":"root","x":-351.64,"y":-573.79,"scaleX":0.6665,"scaleY":0.6665}],"slots":[{"name":"activityFrame169","bone":"layout-size"},{"name":"layout-size","bone":"layout-size","attachment":"layout-size-minimum-size"},{"name":"ring-1","bone":"ring-1","attachment":"ring-1"},{"name":"ring-2","bone":"ring-2","attachment":"ring-1"},{"name":"ring-3","bone":"ring-3","attachment":"ring-1"},{"name":"tail","bone":"tail-end","attachment":"tail"},{"name":"left arm","bone":"arm-left-end","attachment":"left arm"},{"name":"body jet bottom smaller","bone":"body jet small","attachment":"body jet bottom smaller"},{"name":"body jet bottom","bone":"body jet","attachment":"body jet bottom"},{"name":"body-top","bone":"body-end","attachment":"body main"},{"name":"body main top","bone":"body-top","attachment":"body main top"},{"name":"neck ring","bone":"neck-jet","attachment":"neck ring"},{"name":"neck light","bone":"neck-jet","attachment":"neck light"},{"name":"right arm","bone":"arm-right-end","attachment":"right arm"},{"name":"left ear flap","bone":"head-ear-left","attachment":"left ear flap"},{"name":"left ear circle","bone":"head-ear-left","attachment":"left ear circle"},{"name":"head-base","bone":"head","attachment":"head"},{"name":"head-goggles","bone":"head-goggles","attachment":"head-goggles"},{"name":"eye-left","bone":"head-eyes","attachment":"eye reg"},{"name":"eye-right","bone":"head-eyes","attachment":"eye reg"},{"name":"head-snout","bone":"snout-end","attachment":"head-snout"},{"name":"head-snout-nose","bone":"snout-nose","attachment":"head-snout-nose"},{"name":"mouth oh","bone":"mouth","attachment":"mouth open"},{"name":"right ear flap","bone":"head-ear-right-end","attachment":"right ear flap"},{"name":"right ear circle","bone":"head-ear-right-top","attachment":"right ear circle"},{"name":"charge-0","bone":"body-charger","attachment":"new-charge-fill-base"},{"name":"charge-1","bone":"body-charger","attachment":"new-charge-fill-base"},{"name":"charge-2","bone":"body-charger","attachment":"new-charge-fill-base"},{"name":"charge-3","bone":"body-charger","attachment":"new-charge-fill-base"},{"name":"charge-4","bone":"body-charger","attachment":"new-charge-fill-base"},{"name":"charge-5","bone":"body-charger","attachment":"new-charge-fill-base"},{"name":"new-charge-overlay","bone":"body-charger","attachment":"new-charge-overlay"}],"ik":[{"name":"arm-left-target","order":1,"bones":["arm-left-top","arm-left-mid"],"target":"arm-left-target"},{"name":"arm-right-target","bones":["arm-right-top","arm-right-mid"],"target":"arm-right-target","bendPositive":false}],"skins":[{"name":"default","attachments":{"body-top":{"body main":{"type":"mesh","uvs":[0.72316,0.02543,0.8491,0.0751,0.9381,0.1575,0.9735,0.22672,0.99462,0.34805,0.99477,0.49438,0.96522,0.66174,0.91863,0.80581,0.85018,0.90425,0.78015,0.94693,0.67273,0.97991,0.57396,0.99526,0.39168,0.995,0.23167,0.95483,0.14254,0.90221,0.06969,0.77816,0.03273,0.65467,0.00543,0.50868,0.00516,0.33904,0.02478,0.22878,0.05099,0.17674,0.10125,0.11117,0.2039,0.04881,0.31516,0.01809,0.39705,0.00483,0.60054,0.00493],"triangles":[23,6,14,1,25,0,1,24,25,22,23,15,1,23,24,21,22,16,23,1,6,20,21,17,3,4,1,3,1,2,19,20,18,20,17,18,7,9,10,8,9,7,10,6,7,5,6,1,5,1,4,10,11,6,6,11,12,12,14,6,13,14,12,23,14,15,22,15,16,21,16,17],"vertices":[2,32,-159.53,86.28,0.10799,29,-72.82,87.76,0.89201,2,32,-137.96,132,0.24926,29,-51.49,133.6,0.75074,2,32,-103.75,163.63,0.39037,29,-17.46,165.41,0.60963,2,32,-75.54,175.69,0.48339,29,10.69,177.62,0.51661,2,32,-26.64,181.73,0.65346,29,59.56,183.91,0.34654,2,32,32,179.67,0.83336,29,118.21,182.17,0.16664,3,33,-30.94,167.27,0.01329,32,98.68,166.35,0.94288,29,184.96,169.21,0.04382,3,33,26.36,148.57,0.11498,32,155.79,147.09,0.87973,29,242.18,150.26,0.00528,3,33,65.16,122.28,0.282,32,194.34,120.43,0.71794,29,280.86,123.8,6.0E-5,2,33,81.58,96,0.42837,32,210.51,93.99,0.57163,2,33,93.77,56.03,0.71544,32,222.3,53.9,0.28456,2,33,98.96,19.43,0.94544,32,227.14,17.26,0.05456,1,33,97.08,-47.8,1,3,33,79.43,-106.4,0.99975,32,206.38,-108.38,2.3E-4,29,294.13,-104.94,2.0E-5,3,33,57.47,-138.73,0.98332,32,184.11,-140.49,0.01413,29,272.03,-137.17,0.00255,3,33,7.04,-164.29,0.87399,32,133.43,-165.57,0.10092,29,221.49,-162.52,0.02509,3,33,-42.83,-176.62,0.68186,32,83.45,-177.41,0.23125,29,171.57,-174.63,0.0869,3,33,-101.61,-185.15,0.43223,32,24.59,-185.37,0.33605,29,112.75,-182.9,0.23172,3,33,-169.62,-183.46,0.21372,32,-43.4,-183.02,0.30375,29,44.76,-180.92,0.48253,3,33,-213.62,-175.06,0.12726,32,-87.32,-174.19,0.22673,29,0.78,-172.32,0.64601,3,33,-234.23,-164.84,0.09771,32,-107.83,-163.77,0.18671,29,-19.78,-162.02,0.71558,3,33,-260.03,-145.61,0.06479,32,-133.44,-144.29,0.13097,29,-45.49,-142.67,0.80423,3,33,-284.03,-107.09,0.03099,32,-157.06,-105.54,0.06008,29,-69.32,-104.05,0.90893,3,33,-295.26,-65.73,0.0103,32,-167.89,-64.07,0.01294,29,-80.38,-62.63,0.97676,3,33,-299.79,-35.38,0.00262,32,-172.12,-33.68,4.5E-4,29,-84.77,-32.27,0.99693,2,32,-169.38,41.36,0.01926,29,-82.42,42.78,0.98074],"hull":26,"edges":[0,50,0,2,2,4,4,6,6,8,8,10,10,12,12,14,14,16,16,18,18,20,20,22,22,24,24,26,26,28,28,30,30,32,32,34,34,36,36,38,38,40,40,42,42,44,44,46,46,48,48,50],"width":369,"height":401}},"body jet bottom":{"body jet bottom":{"x":7.5,"y":-2.03,"rotation":87.61,"width":178,"height":70}},"body jet bottom smaller":{"body jet bottom smaller":{"x":-2.23,"y":-3.55,"rotation":88.41,"width":67,"height":41}},"body main top":{"body main top":{"x":-30.13,"y":-1.3,"rotation":90,"width":290,"height":114}},"charge-0":{"new-charge-fill-base":{"color":"6df13aff","x":76.95,"y":-20.54,"scaleX":0.4677,"scaleY":0.4355,"rotation":-87.97,"width":205,"height":62}},"charge-1":{"new-charge-fill-base":{"color":"6df13aff","x":49.99,"y":-21.31,"scaleX":0.4677,"scaleY":0.4355,"rotation":-87.97,"width":205,"height":62}},"charge-2":{"new-charge-fill-base":{"color":"6df13aff","x":19.31,"y":-19.17,"scaleX":0.4677,"scaleY":0.4355,"rotation":-87.97,"width":205,"height":62}},"charge-3":{"new-charge-fill-base":{"color":"ba94b8ff","x":-10.39,"y":-20.64,"scaleX":0.4677,"scaleY":0.4355,"rotation":-87.97,"width":205,"height":62}},"charge-4":{"new-charge-fill-base":{"color":"ba94b8ff","x":-43.01,"y":-19.25,"scaleX":0.5027,"scaleY":0.5105,"rotation":-87.97,"width":205,"height":62}},"charge-5":{"new-charge-fill-base":{"color":"ba94b8ff","x":-74.41,"y":-18.68,"scaleX":0.5027,"scaleY":0.5105,"rotation":-87.97,"width":205,"height":62}},"eye-left":{"eye narrow":{"path":"eye narrow-left","x":-5.88,"y":-24.65,"rotation":-90.37,"width":201,"height":48},"eye reg":{"path":"eye reg-left","x":-4.23,"y":-18.99,"rotation":-90.37,"width":163,"height":107},"eyes half moon down":{"path":"eye down half moon-left","x":-9.44,"y":-21.04,"rotation":-90.37,"width":170,"height":87},"eye up half moon":{"path":"eye up half moon-left","x":4.96,"y":-12.17,"rotation":-90.37,"width":169,"height":79}},"eye-right":{"eye narrow":{"path":"eye narrow-right","x":-5.88,"y":-24.65,"rotation":-90.37,"width":201,"height":48},"eye reg":{"path":"eye reg-right","x":-4.23,"y":-18.99,"rotation":-90.37,"width":163,"height":107},"eyes half moon down":{"path":"eye down half moon-right","x":-9.44,"y":-21.04,"rotation":-90.37,"width":170,"height":87},"eye up half moon":{"path":"eye up half moon-right","x":4.96,"y":-12.17,"rotation":-90.37,"width":169,"height":79}},"head-base":{"head":{"x":210.21,"y":29.51,"rotation":-90.37,"width":547,"height":475}},"head-goggles":{"head-goggles":{"x":-45.87,"y":-22.82,"rotation":-80,"width":338,"height":277}},"head-snout":{"head-snout":{"type":"mesh","uvs":[0.30467,0.01636,0.41506,0.09065,0.55074,0.26571,0.70993,0.559,0.80372,0.7154,0.8898,0.82078,0.99251,0.90873,0.8985,0.96199,0.75949,1,0.58899,1,0.44952,0.96853,0.28665,0.88975,0.16214,0.77499,0.07427,0.65215,0.02105,0.52615,0,0.40915,0,0.28622,0.0286,0.15924,0.09054,0.05848,0.17801,0.01562],"triangles":[0,13,19,1,13,0,1,12,13,18,19,14,19,13,14,16,17,18,18,14,15,18,15,16,10,11,3,2,11,12,11,2,3,2,12,1,8,5,7,8,4,5,8,9,4,4,9,3,9,10,3,7,5,6],"vertices":[2,19,215.39,-99.98,0.0653,20,116.98,-48.56,0.9347,2,19,165.16,-113.68,0.31696,20,80.12,-85.32,0.68304,3,18,188.33,-133.61,0.01121,19,86.21,-111.08,0.83627,20,10.23,-122.14,0.15251,2,18,89.93,-77.78,0.63952,19,-24.47,-87.61,0.36048,2,18,34.01,-49.53,0.97956,19,-86.31,-77.6,0.02044,1,18,-12.51,-34.42,1,1,18,-63.28,-27.1,1,1,18,-33.62,4.11,1,1,18,15.37,38.71,1,2,18,81.3,67.94,0.98379,19,-76.76,48.67,0.01621,2,18,139.19,82.93,0.60549,19,-26.11,80.46,0.39451,3,18,212.07,88.51,0.10699,19,41.66,107.83,0.85874,20,-136.83,46.01,0.03427,3,18,274.63,77.33,0.00583,19,104.68,116.09,0.73772,20,-86.17,84.38,0.25645,2,19,157.75,112.21,0.40446,20,-38.13,107.28,0.59554,2,19,200.5,97.87,0.15145,20,6.1,115.99,0.84855,2,19,231.2,76.61,0.03881,20,43.31,112.71,0.96119,2,19,256.46,48.08,0.00203,20,79.38,100.42,0.99797,1,20,112.73,76.27,1,1,20,133.85,41.39,1,2,19,255.66,-64.65,1.9E-4,20,134.48,2.08,0.99981],"hull":20,"edges":[0,38,0,2,2,4,4,6,6,8,8,10,10,12,12,14,14,16,16,18,18,20,20,22,22,24,24,26,26,28,28,30,30,32,32,34,34,36,36,38],"width":423,"height":310}},"head-snout-nose":{"head-snout-nose":{"x":-37.92,"y":-0.52,"rotation":-110.88,"width":201,"height":108}},"layout-size":{"layout-size-minimum-size":{"type":"boundingbox","vertexCount":4,"vertices":[-1086.35,3.01,-1086.31,1491,1073.85,1490.85,1073.97,3.08]},"layout-size-with-safe-areas":{"type":"boundingbox","vertexCount":4,"vertices":[-1446.23,2.95,-1446.19,1490.94,1433.73,1490.83,1433.85,3.05]}},"left arm":{"left arm":{"type":"mesh","uvs":[0.91558,0.0371,0.97421,0.08055,1,0.12661,1,0.14658,0.92967,0.31784,0.81816,0.45033,0.6591,0.63931,0.54004,0.74555,0.42549,0.84776,0.22409,0.97707,0.17755,0.99099,0.0611,0.99112,0,0.87006,0,0.83479,0.02441,0.66194,0.0601,0.54357,0.1066,0.45213,0.14606,0.37453,0.22355,0.28728,0.30821,0.19196,0.38833,0.12398,0.45267,0.06939,0.64817,0.00918,0.80204,0.00919],"triangles":[1,2,3,3,4,0,3,0,1,23,4,22,4,23,0,22,5,21,4,5,22,5,20,21,5,19,20,6,19,5,18,19,6,7,18,6,17,18,7,16,17,7,15,16,7,8,14,15,15,7,8,14,8,9,14,9,13,13,10,12,9,10,13,11,12,10],"vertices":[1,6,-27.4,-0.55,1,1,6,-29.45,14.89,1,1,6,-26.21,25.76,1,1,6,-23.14,28.8,1,1,6,13.66,44.16,1,2,25,-68.66,47.44,0.06834,6,50.64,47.44,0.93166,2,25,-15.92,52.11,0.16581,6,103.38,52.11,0.83419,3,26,-61.39,50.26,0.04478,25,18.14,50.26,0.52543,6,137.44,50.26,0.42979,3,26,-28.62,48.49,0.08787,25,50.91,48.49,0.87141,6,170.21,48.49,0.04073,2,26,21.25,37.71,0.82945,25,100.78,37.71,0.17055,2,26,30.32,32.8,0.91863,25,109.85,32.8,0.08137,2,26,47.68,15.25,0.99981,25,127.21,15.25,1.9E-4,2,26,38.17,-12.33,0.99933,25,117.7,-12.33,6.7E-4,2,26,32.74,-17.69,0.9862,25,112.28,-17.69,0.0138,2,26,2.54,-40.23,0.39142,25,82.07,-40.23,0.60858,3,26,-20.98,-52.8,0.0844,25,58.55,-52.8,0.89989,6,177.85,-52.8,0.01571,3,26,-41.96,-59.66,0.03886,25,37.57,-59.66,0.82745,6,156.87,-59.66,0.13369,3,26,-59.77,-65.48,2.2E-4,25,19.77,-65.48,0.76596,6,139.07,-65.48,0.23382,3,26,-84.72,-67.02,1.1E-4,25,-5.19,-67.02,0.49597,6,114.11,-67.02,0.50391,2,25,-32.45,-68.71,0.20102,6,86.85,-68.71,0.79898,2,25,-54.83,-66.93,0.10225,6,64.47,-66.93,0.89775,2,25,-72.8,-65.51,0.02293,6,46.5,-65.51,0.97707,1,6,8.13,-45.14,1,1,6,-14.79,-21.92,1],"hull":24,"edges":[0,46,0,2,2,4,4,6,6,8,16,18,18,20,20,22,22,24,24,26,26,28,28,30,42,44,44,46,34,36,36,38,30,32,32,34,38,40,40,42,12,14,14,16,8,10,10,12],"width":212,"height":216}},"left ear circle":{"left ear circle":{"x":41.59,"y":19.73,"rotation":121.41,"width":158,"height":190}},"left ear flap":{"left ear flap":{"x":161.61,"y":22.73,"rotation":121.41,"width":276,"height":382}},"mouth oh":{"mouth oh":{"x":1.68,"y":42.67,"rotation":-90.37,"width":55,"height":68},"mouth open":{"x":-3.11,"y":-1.8,"rotation":-90.37,"width":152,"height":83},"mouth smile side":{"x":9.31,"y":-14.38,"rotation":-90.37,"width":133,"height":64},"mouth wide open":{"x":-0.08,"y":3.18,"rotation":-90.37,"width":175,"height":140}},"neck light":{"neck light":{"x":-9.86,"y":-0.58,"rotation":88.24,"width":129,"height":42}},"neck ring":{"neck ring":{"x":-5.86,"y":-0.7,"rotation":88.24,"width":192,"height":70}},"new-charge-overlay":{"new-charge-overlay":{"x":-10.81,"y":-20.06,"scaleX":0.4881,"scaleY":0.4881,"rotation":88.85,"width":269,"height":481}},"right arm":{"right arm":{"type":"mesh","uvs":[0.54652,0.06956,0.61994,0.13115,0.68944,0.18945,0.76978,0.27994,0.85481,0.3757,0.90101,0.46723,0.93367,0.53192,0.97622,0.66205,1,0.83793,0.96341,0.96049,0.8748,1,0.83869,1,0.7351,0.95575,0.52378,0.80884,0.31274,0.60529,0.14735,0.40952,0.04211,0.25451,0,0.13608,0,0.11085,0.07195,0.04018,0.19756,0.00918,0.35085,0.00898],"triangles":[17,18,19,16,17,19,20,16,19,15,16,20,21,15,20,0,15,21,1,15,0,14,1,2,14,2,3,15,1,14,4,13,14,4,14,3,13,4,5,13,5,6,13,6,7,12,13,7,8,12,7,8,11,12,8,10,11,9,10,8],"vertices":[2,23,-60.66,81.33,0.0795,5,63.7,81.33,0.9205,2,23,-40.19,81.57,0.20344,5,84.17,81.57,0.79656,2,23,-20.81,81.79,0.32075,5,103.55,81.79,0.67925,3,24,-78.03,78.3,0.00403,23,4.88,78.3,0.5652,5,129.24,78.3,0.43078,3,24,-50.84,74.6,0.00829,23,32.07,74.6,0.82387,5,156.43,74.6,0.16784,3,24,-30.45,66.17,0.08115,23,52.46,66.17,0.8408,5,176.82,66.17,0.07806,3,24,-16.04,60.22,0.13265,23,66.87,60.22,0.85276,5,191.23,60.22,0.01459,2,24,9.26,45,0.4814,23,92.17,45,0.5186,2,24,38.07,19.73,0.98401,23,120.98,19.73,0.01599,1,24,49.66,-5.3,1,2,24,41.15,-24.09,0.99896,23,124.06,-24.09,0.00104,2,24,35.38,-29.13,0.98727,23,118.29,-29.13,0.01273,2,24,12.56,-36.4,0.73645,23,95.47,-36.4,0.26355,3,24,-42.05,-42.02,0.00232,23,40.86,-42.02,0.99196,5,165.22,-42.02,0.00572,2,23,-21.76,-38.39,0.15039,5,102.6,-38.39,0.84961,1,5,48.37,-29.66,1,1,5,9.53,-19.15,1,1,5,-14.04,-5.78,1,1,5,-17.62,-1.68,1,1,5,-16.2,19.85,1,1,5,-0.56,42.43,1,2,23,-100.5,63.86,0.00422,5,23.86,63.86,0.99578],"hull":22,"edges":[0,42,12,14,14,16,16,18,18,20,20,22,22,24,24,26,26,28,28,30,30,32,32,34,34,36,36,38,38,40,40,42,4,6,6,8,8,10,10,12,0,2,2,4],"width":212,"height":216}},"right ear circle":{"right ear circle":{"x":20.31,"y":-5.86,"rotation":78.84,"width":145,"height":198}},"right ear flap":{"right ear flap":{"type":"mesh","uvs":[0.40898,0,0.66078,0.07379,0.96076,0.57678,1,0.76986,1,0.84936,0.85023,0.99451,0.44476,0.99639,0.14641,0.89555,0.00908,0.67805,0.00942,0.31351,0.13564,0.04377,0.29736,0],"triangles":[9,1,2,9,10,1,1,10,0,10,11,0,2,8,9,5,6,4,3,4,6,3,7,8,3,6,7,3,8,2],"vertices":[1,9,-71.6,11.37,1,1,9,-31.39,58.1,1,3,17,-39.39,82.82,0.32352,16,81.28,83.42,0.5262,9,184.29,80.68,0.15028,3,17,40.52,79.24,0.94711,16,161.1,78.36,0.04852,9,263.95,73.49,0.00437,3,17,72.91,74.36,0.9976,16,193.4,72.88,0.00234,9,296.09,67.15,6.0E-5,1,17,127.29,33.91,1,1,17,115.2,-51.61,1,2,17,64.65,-108.26,0.92227,16,181.76,-109.55,0.07773,2,17,-28.32,-123.84,0.403,16,88.52,-123.41,0.597,3,17,-176.82,-101.4,0.00158,16,-59.54,-98.23,0.61616,9,38.65,-97.13,0.38226,2,16,-164.62,-53.14,0.02073,9,-65.18,-49.24,0.97927,2,16,-176.64,-16.16,0.00149,9,-76.2,-11.96,0.99851],"hull":12,"edges":[0,22,0,2,2,4,4,6,6,8,8,10,10,12,12,14,14,16,16,18,18,20,20,22],"width":213,"height":412}},"ring-1":{"ring-1":{"path":"ring top","x":43.01,"y":7.66,"rotation":90,"width":268,"height":102}},"ring-2":{"ring-1":{"path":"ring top","x":43.01,"y":7.66,"rotation":90,"width":268,"height":102}},"ring-3":{"ring-1":{"path":"ring top","x":43.01,"y":7.66,"rotation":90,"width":268,"height":102}},"tail":{"tail":{"type":"mesh","uvs":[0.93242,0.01741,0.98988,0.11396,0.98998,0.2817,0.95948,0.43826,0.89793,0.62126,0.80327,0.80152,0.67594,0.91947,0.56528,0.98239,0.36695,0.98242,0.26183,0.94036,0.14902,0.84447,0.09772,0.778,0.01021,0.62818,0.01007,0.4754,0.0632,0.41361,0.20776,0.36361,0.30896,0.32861,0.37428,0.30601,0.43031,0.28226,0.51329,0.22618,0.63969,0.14076,0.82269,0.01709],"triangles":[9,16,8,10,15,9,9,15,16,10,11,15,12,14,11,11,14,15,12,13,14,7,8,18,8,17,18,8,16,17,6,7,19,7,18,19,6,19,5,5,19,20,5,20,4,4,20,3,2,3,21,21,3,20,2,0,1,0,2,21],"vertices":[1,28,66.23,6.32,1,1,28,69.85,-8.81,1,3,28,59.82,-24.9,0.99675,27,131.95,-7.11,0.0032,4,187.57,35.59,5.0E-5,3,28,45.45,-36.78,0.95157,27,121.5,-22.54,0.04515,4,182.43,17.67,0.00328,3,28,24.42,-48.02,0.79471,27,104.46,-39.24,0.18119,4,171.44,-3.49,0.0241,3,28,-1.87,-55.61,0.52874,27,81.36,-53.9,0.37795,4,154.05,-24.61,0.09331,3,28,-29.77,-53.89,0.25777,27,54.1,-60.07,0.51526,4,130.05,-38.97,0.22696,3,28,-51.65,-48.6,0.0813,27,31.61,-61.14,0.41945,4,109.02,-46.97,0.49926,3,28,-84.11,-28.31,0.01718,27,-5.24,-50.78,0.22184,4,70.77,-48.59,0.76098,2,27,-23.48,-40.71,0.04258,4,50.3,-44.7,0.95742,2,27,-41.51,-24.38,0.00236,4,28.09,-34.79,0.99764,1,4,17.88,-27.71,1,1,4,0.29,-11.51,1,2,27,-56.03,23.02,2.3E-4,4,-0.46,5.74,0.99977,2,27,-44.27,26.97,0.09765,4,9.49,13.15,0.90235,2,27,-15.88,24.86,0.40905,4,37.12,19.97,0.59095,2,27,3.99,23.38,0.74216,4,56.47,24.75,0.25784,3,28,-42.4,35.75,8.0E-5,27,16.82,22.42,0.97799,4,68.96,27.83,0.02193,2,28,-31.81,32.3,0.02296,27,27.95,22.08,0.97704,2,28,-14.87,29.18,0.27295,27,45.09,23.84,0.72705,2,28,10.93,24.44,0.6062,27,71.18,26.53,0.3938,2,28,48.29,17.57,0.91666,27,108.97,30.42,0.08334],"hull":22,"edges":[0,42,0,2,2,4,4,6,6,8,8,10,10,12,12,14,14,16,16,18,18,20,20,22,22,24,24,26,26,28,34,36,28,30,40,42,36,38,38,40,30,32,32,34],"width":193,"height":113}}}}],"animations":{"blink":{"slots":{"eye-left":{"attachment":[{"time":2.1,"name":"eye narrow"},{"time":2.1667,"name":"eye reg"}]},"eye-right":{"attachment":[{"time":2.1,"name":"eye narrow"},{"time":2.1667,"name":"eye reg"},{"time":4.6667,"name":"eye reg"}]}}},"head tilt and bob":{"slots":{"mouth oh":{"attachment":[{"name":"mouth smile side"},{"time":0.2,"name":"mouth open"}]}},"bones":{"head":{"rotate":[{"curve":[0.067,0,0.133,-11.82]},{"time":0.2,"value":-11.82,"curve":[0.589,-11.82,0.978,-12.35]},{"time":1.3667,"value":-11.82,"curve":[6.427,-4.91,11.8,1.48]},{"time":16}]},"head-ear-right-top":{"rotate":[{"time":0.0667,"curve":[0.122,-3.81,0.178,-11.42]},{"time":0.2333,"value":-11.42,"curve":[0.322,-11.42,0.411,8.95]},{"time":0.5,"value":8.95,"curve":[0.567,8.95,0.633,-1.46]},{"time":0.7,"value":-1.46,"curve":[0.756,-1.46,0.811,2.19]},{"time":0.8667,"value":4.02,"curve":[0.922,5.84,0.978,1.67]},{"time":1.0333,"value":1.67}]},"head-ear-left":{"rotate":[{"time":0.0667,"curve":[0.111,12.65,0.156,37.95]},{"time":0.2,"value":37.95,"curve":[0.256,37.95,0.311,7.54]},{"time":0.3667,"value":7.54,"curve":[0.456,7.54,0.544,22.3]},{"time":0.6333,"value":22.3,"curve":[0.744,22.3,0.856,11.22]},{"time":0.9667,"value":11.22,"curve":[1.089,11.22,1.211,15.3]},{"time":1.3333,"value":17.35}]},"mouth":{"scale":[{"time":3.6333},{"time":10.0333,"x":0.415}]}}},"idle":{"bones":{"body-main":{"translate":[{"curve":[0.444,0,0.885,-1.94,0.444,0,0.889,25.08]},{"time":1.3333,"x":-0.77,"y":25.08,"curve":[1.889,0.68,2.444,0,1.889,25.08,2.444,0]},{"time":3}]},"arm-left-top":{"rotate":[{"curve":[0.456,0,0.911,9.62]},{"time":1.3667,"value":9.62,"curve":[1.833,9.62,2.3,0]},{"time":2.7667}]},"arm-right-top":{"rotate":[{"curve":[0.5,0,1,-9.45]},{"time":1.5,"value":-9.45,"curve":[2,-9.45,2.5,0]},{"time":3}]},"body jet":{"translate":[{},{"time":1.6667,"x":10.82,"y":0.12},{"time":2.9667}]},"tail-top":{"translate":[{"x":-18.7,"y":-28.27}]}}},"ring1":{"bones":{"ring-1":{"translate":[{},{"time":0.6667,"x":11.26,"y":314.69,"curve":"stepped"},{"time":1.3333,"x":11.26,"y":314.69}]}}},"ring2":{"bones":{"ring-2":{"translate":[{"time":0.6667},{"time":1.3333,"x":-8.14,"y":-310.73}]}}},"tail wag":{"bones":{"tail-top":{"scale":[{"x":0.79,"y":1.15},{"time":0.2,"x":0.98,"curve":[0.278,0.98,0.356,0.79,0.278,1,0.356,1.15]},{"time":0.4333,"x":0.79,"y":1.15}],"shear":[{"x":14.09},{"time":0.2,"x":-22.17,"curve":[0.278,-22.17,0.356,14.09,0.278,0,0.356,0]},{"time":0.4333,"x":14.09}]}}}}}